{
    "id": 50963,
    "titulo": "Sampaio desconhece dificuldades na obten\u00e7\u00e3o de vistos no Brasil",
    "tituloNoticia": "Sampaio desconhece dificuldades na obten\u00e7\u00e3o de vistos no Brasil",
    "tituloOriginal": null,
    "descricao": "",
    "textoAlternativo": null,
    "url": "/2001/11/22/politica/noticia/sampaio-desconhece-dificuldades-na-obtencao-de-vistos-no-brasil-50963",
    "multimediaPrincipal": "https://imagens.publico.pt/imagens.aspx/35417?tp=UH&db=IMAGENS&type=JPG",
    "multimediaPrincipalLegenda": "Sampaio destacou a nova fase das boas rela\u00e7\u00f5es entre Portugal e o Brasil",
    "hasLive": false,
    "pontuacao": null,
    "numeroComentarios": 0,
    "lead": "O Presidente da Rep\u00fablica, Jorge Sampaio, disse ontem, em S\u00e3o Paulo, desconhecer os problemas que os profissionais portugueses t\u00eam sentido na obten\u00e7\u00e3o de vistos de trabalho no Brasil. O chefe de Estado passou, assim, ao lado de uma quest\u00e3o que tem suscitado diversas queixas por parte dos empres\u00e1rios portugueses que pretendem entrar no mercado brasileiro.",
    "shortUrl": "/n50963",
    "titulo_Mobile": null,
    "subtitulo": "PR fez escala em S\u00e3o Paulo antes da Cimeira Ibero-Americana",
    "rubricTag": null,
    "rubrica": "PR fez escala em S\u00e3o Paulo antes da Cimeira Ibero-Americana",
    "rubricUrl": null,
    "tipo": "NOTICIA",
    "emActualizacao": false,
    "fechaComentarios": false,
    "emDirecto": false,
    "facebook": 0,
    "twitter": 0,
    "google": 0,
    "fonteMultimediaPrincipal": "IMAGENS",
    "palavraChave": null,
    "itemId": "NOTICIA_50963",
    "tokenTipo": null,
    "numPartilhas": 0,
    "numComentarios": 0,
    "html": null,
    "tipoLayout": "MULTIMEDIA_NORMAL",
    "caixaId": null,
    "isOpinion": false,
    "fullUrl": "/2001/11/22/politica/noticia/sampaio-desconhece-dificuldades-na-obtencao-de-vistos-no-brasil-50963",
    "prioridade": 3,
    "isPreview": false,
    "escondeImagem": false,
    "aoMinuto": false,
    "isFeature": false,
    "slug": "sampaio-desconhece-dificuldades-na-obtencao-de-vistos-no-brasil-50963",
    "cleanTitle": "Sampaio desconhece dificuldades na obten\u00e7\u00e3o de vistos no Brasil",
    "isHtml": false,
    "shareUrl": "https://www.publico.pt/2001/11/22/politica/noticia/sampaio-desconhece-dificuldades-na-obtencao-de-vistos-no-brasil-50963",
    "newsUrls": [],
    "isImagePortait": false,
    "cardInfo": {
        "css": [
            "card--f",
            "tone--news"
        ],
        "showMedia": false,
        "maxLinks": 0,
        "isHeadlineBlock": false,
        "showLead": false,
        "mediaCss": ""
    },
    "brand": null,
    "caixaConteudo": null,
    "dataActualizacao": null,
    "autores": [],
    "dataSheet": null,
    "mapUrl": null,
    "tags": [
        {
            "id": 332,
            "nome": "Brasil",
            "slug": "brasil",
            "tagEn": null,
            "isPrincipal": false,
            "isVisible": true,
            "urlRoute": "/tbrasil",
            "isPrincipalParaArtigo": false,
            "isTimeLine": false,
            "forcaConteudoAberto": false,
            "follow_type": null,
            "descricao": null,
            "imagem": null,
            "html": null,
            "isForForuns": false,
            "isUsedInForuns": false
        },
        {
            "id": 435,
            "nome": "Jorge Sampaio",
            "slug": "jorge-sampaio",
            "tagEn": null,
            "isPrincipal": false,
            "isVisible": true,
            "urlRoute": "/tjorge-sampaio",
            "isPrincipalParaArtigo": false,
            "isTimeLine": false,
            "forcaConteudoAberto": false,
            "follow_type": null,
            "descricao": null,
            "imagem": null,
            "html": null,
            "isForForuns": false,
            "isUsedInForuns": false
        },
        {
            "id": 870,
            "nome": "Pol\u00edtica",
            "slug": "politica",
            "tagEn": null,
            "isPrincipal": true,
            "isVisible": true,
            "urlRoute": "/tpolitica",
            "isPrincipalParaArtigo": false,
            "isTimeLine": false,
            "forcaConteudoAberto": false,
            "follow_type": null,
            "descricao": null,
            "imagem": null,
            "html": null,
            "isForForuns": false,
            "isUsedInForuns": false
        }
    ],
    "imagens": [
        {
            "w": null,
            "h": null,
            "largura": null,
            "altura": null,
            "nome": "35417_SampaioTiagoPetingaL.jpg",
            "legenda": "Sampaio destacou a nova fase das boas rela\u00e7\u00f5es entre Portugal e o Brasil",
            "autor": "Tiago Petinga/Lusa",
            "tipo": "JPG",
            "url": "https://imagens.publico.pt/imagens.aspx/35417?tp=UH&db=IMAGENS&type=JPG",
            "is_vertical": false,
            "tags": "Sampaio destacou a nova fase das boas rela\u00e7\u00f5es entre Portugal e o Brasil",
            "translations": null
        }
    ],
    "criticas": [],
    "videos": [],
    "fotogalerias": [],
    "ficheiros": [],
    "links": [],
    "infografias": [],
    "elementos": [],
    "fichaTecnica": [],
    "audios": [],
    "charCount": 0,
    "iconography": "",
    "isSponsorContent": false,
    "isClubeP": false,
    "isItemOpinion": false,
    "isInlineMedia": false,
    "hasManualSubtitle": true,
    "isMultipleRubric": false,
    "socialUmage": null,
    "socialTitle": "PR fez escala em S\u00e3o Paulo antes da Cimeira Ibero-Americana. Sampaio desconhece dificuldades na obten\u00e7\u00e3o de vistos no Brasil",
    "isLongForm": false,
    "isClosed": false,
    "isExclusive": false,
    "satelliteName": "",
    "userLibraryStatus": null,
    "maxParagraph": -1,
    "isHeadline": false,
    "wordCount": 158,
    "extra4": null,
    "partners": null,
    "props": null,
    "name": "0050963.json",
    "dct": "2001-11-22T09:29:00",
    "text": "O embaixador portugu\u00eas naquele pa\u00eds, Ant\u00f3nio Franco, reconheceu, contudo, a exist\u00eancia dessas dificuldades e garantiu que ir\u00e1 negociar com as autoridades de Bras\u00edlia uma solu\u00e7\u00e3o para o problema. No entanto, o diplomata nacional recordou que os entraves n\u00e3o se fazem sentir, apenas, entre os portugueses que v\u00e3o para o Brasil, mas tamb\u00e9m entre os brasileiros que querem trabalhar em Portugal, noticia a Lusa.Jorge Sampaio aproveitou a sua presen\u00e7a na Cimeira Ibero-Americana - que come\u00e7a amanh\u00e3 e termina no s\u00e1bado - para fazer uma escala em S\u00e3o Paulo, onde foi recebido ontem \u00e0 noite, por cerca de mil pessoas, na Casa de Portugal, sede do consulado geral naquela cidade.No seu discurso, perante uma plateia recheada de empres\u00e1rios portugueses e brasileiros, bem como representantes da comunidade lusa no Brasil, o Presidente da Rep\u00fablica destacou a nova fase das boas rela\u00e7\u00f5es entre os dois pa\u00edses, especialmente depois de Portugal se ter tornado o terceiro maior investidor estrangeiro no Brasil.",
    "language": "portuguese"
}