{
    "id": 16767,
    "titulo": "Lisboa encerra com leves ganhos",
    "tituloNoticia": "Lisboa encerra com leves ganhos",
    "tituloOriginal": null,
    "descricao": "",
    "textoAlternativo": null,
    "url": "/2001/03/28/economia/noticia/lisboa-encerra-com-leves-ganhos-16767",
    "multimediaPrincipal": null,
    "multimediaPrincipalLegenda": null,
    "hasLive": false,
    "pontuacao": null,
    "numeroComentarios": 0,
    "lead": "A Bolsa de Valores de Lisboa e Porto encerrou hoje em alta ligeira, em contraciclo com as restantes pra\u00e7as europeias. Tanto o PSI-20 como o PSI-30 ganharam 0,39 por cento.",
    "shortUrl": "/n16767",
    "titulo_Mobile": null,
    "subtitulo": "Ambos os \u00edndices subiram 0,39 por cento",
    "rubricTag": null,
    "rubrica": "Ambos os \u00edndices subiram 0,39 por cento",
    "rubricUrl": null,
    "tipo": "NOTICIA",
    "emActualizacao": false,
    "fechaComentarios": false,
    "emDirecto": false,
    "facebook": 0,
    "twitter": 0,
    "google": 0,
    "fonteMultimediaPrincipal": null,
    "palavraChave": null,
    "itemId": "NOTICIA_16767",
    "tokenTipo": null,
    "numPartilhas": 0,
    "numComentarios": 0,
    "html": null,
    "tipoLayout": "MULTIMEDIA_NORMAL",
    "caixaId": null,
    "isOpinion": false,
    "fullUrl": "/2001/03/28/economia/noticia/lisboa-encerra-com-leves-ganhos-16767",
    "prioridade": 3,
    "isPreview": false,
    "escondeImagem": false,
    "aoMinuto": false,
    "isFeature": false,
    "slug": "lisboa-encerra-com-leves-ganhos-16767",
    "cleanTitle": "Lisboa encerra com leves ganhos",
    "isHtml": false,
    "shareUrl": "https://www.publico.pt/2001/03/28/economia/noticia/lisboa-encerra-com-leves-ganhos-16767",
    "newsUrls": [],
    "isImagePortait": false,
    "cardInfo": {
        "css": [
            "card--f",
            "tone--news"
        ],
        "showMedia": false,
        "maxLinks": 0,
        "isHeadlineBlock": false,
        "showLead": false,
        "mediaCss": ""
    },
    "brand": null,
    "caixaConteudo": null,
    "dataActualizacao": null,
    "autores": [],
    "dataSheet": null,
    "mapUrl": null,
    "tags": [
        {
            "id": 479,
            "nome": "Bolsa",
            "slug": "bolsa",
            "tagEn": null,
            "isPrincipal": false,
            "isVisible": true,
            "urlRoute": "/tbolsa",
            "isPrincipalParaArtigo": false,
            "isTimeLine": false,
            "forcaConteudoAberto": false,
            "follow_type": null,
            "descricao": null,
            "imagem": null,
            "html": null,
            "isForForuns": false,
            "isUsedInForuns": false
        },
        {
            "id": 480,
            "nome": "PSI 20",
            "slug": "psi-20",
            "tagEn": null,
            "isPrincipal": false,
            "isVisible": true,
            "urlRoute": "/tpsi-20",
            "isPrincipalParaArtigo": false,
            "isTimeLine": false,
            "forcaConteudoAberto": false,
            "follow_type": null,
            "descricao": null,
            "imagem": null,
            "html": null,
            "isForForuns": false,
            "isUsedInForuns": false
        },
        {
            "id": 644,
            "nome": "Lisboa",
            "slug": "lisboa",
            "tagEn": null,
            "isPrincipal": false,
            "isVisible": true,
            "urlRoute": "/tlisboa",
            "isPrincipalParaArtigo": false,
            "isTimeLine": false,
            "forcaConteudoAberto": false,
            "follow_type": null,
            "descricao": null,
            "imagem": null,
            "html": null,
            "isForForuns": false,
            "isUsedInForuns": false
        },
        {
            "id": 645,
            "nome": "Porto",
            "slug": "porto",
            "tagEn": null,
            "isPrincipal": false,
            "isVisible": true,
            "urlRoute": "/tporto",
            "isPrincipalParaArtigo": false,
            "isTimeLine": false,
            "forcaConteudoAberto": false,
            "follow_type": null,
            "descricao": null,
            "imagem": null,
            "html": null,
            "isForForuns": false,
            "isUsedInForuns": false
        },
        {
            "id": 866,
            "nome": "Economia",
            "slug": "economia",
            "tagEn": null,
            "isPrincipal": true,
            "isVisible": true,
            "urlRoute": "/teconomia",
            "isPrincipalParaArtigo": false,
            "isTimeLine": false,
            "forcaConteudoAberto": false,
            "follow_type": null,
            "descricao": null,
            "imagem": null,
            "html": null,
            "isForForuns": false,
            "isUsedInForuns": false
        }
    ],
    "imagens": [],
    "criticas": [],
    "videos": [],
    "fotogalerias": [],
    "ficheiros": [],
    "links": [],
    "infografias": [],
    "elementos": [],
    "fichaTecnica": [],
    "audios": [],
    "charCount": 0,
    "iconography": "",
    "isSponsorContent": false,
    "isClubeP": false,
    "isItemOpinion": false,
    "isInlineMedia": false,
    "hasManualSubtitle": true,
    "isMultipleRubric": false,
    "socialUmage": null,
    "socialTitle": "Ambos os \u00edndices subiram 0,39 por cento. Lisboa encerra com leves ganhos",
    "isLongForm": false,
    "isClosed": false,
    "isExclusive": false,
    "satelliteName": "",
    "userLibraryStatus": null,
    "maxParagraph": -1,
    "isHeadline": false,
    "wordCount": 0,
    "extra4": null,
    "partners": null,
    "props": null,
    "name": "0016767.json",
    "dct": "2001-03-28T16:36:00",
    "text": "",
    "language": "portuguese"
}