{
    "id": 61970,
    "titulo": "Lagos vive no p\u00e2nico mas sem confrontos",
    "tituloNoticia": "Lagos vive no p\u00e2nico mas sem confrontos",
    "tituloOriginal": null,
    "descricao": "",
    "textoAlternativo": null,
    "url": "/2002/02/05/mundo/noticia/lagos-vive-no-panico-mas-sem-confrontos-61970",
    "multimediaPrincipal": null,
    "multimediaPrincipalLegenda": null,
    "hasLive": false,
    "pontuacao": null,
    "numeroComentarios": 0,
    "lead": "Os bairros de Lagos, a maior cidade da Nig\u00e9ria, vivem hoje num clima tenso, com popula\u00e7\u00f5es em p\u00e2nico e registo de fuga de centenas de pessoas. No entanto, n\u00e3o ocorreu nenhum confronto, informou a pol\u00edcia.",
    "shortUrl": "/n61970",
    "titulo_Mobile": null,
    "subtitulo": "Nig\u00e9ria",
    "rubricTag": null,
    "rubrica": "Nig\u00e9ria",
    "rubricUrl": null,
    "tipo": "NOTICIA",
    "emActualizacao": false,
    "fechaComentarios": false,
    "emDirecto": false,
    "facebook": 0,
    "twitter": 0,
    "google": 0,
    "fonteMultimediaPrincipal": null,
    "palavraChave": null,
    "itemId": "NOTICIA_61970",
    "tokenTipo": null,
    "numPartilhas": 0,
    "numComentarios": 0,
    "html": null,
    "tipoLayout": "MULTIMEDIA_NORMAL",
    "caixaId": null,
    "isOpinion": false,
    "fullUrl": "/2002/02/05/mundo/noticia/lagos-vive-no-panico-mas-sem-confrontos-61970",
    "prioridade": 3,
    "isPreview": false,
    "escondeImagem": false,
    "aoMinuto": false,
    "isFeature": false,
    "slug": "lagos-vive-no-panico-mas-sem-confrontos-61970",
    "cleanTitle": "Lagos vive no p\u00e2nico mas sem confrontos",
    "isHtml": false,
    "shareUrl": "https://www.publico.pt/2002/02/05/mundo/noticia/lagos-vive-no-panico-mas-sem-confrontos-61970",
    "newsUrls": [],
    "isImagePortait": false,
    "cardInfo": {
        "css": [
            "card--f",
            "tone--news"
        ],
        "showMedia": false,
        "maxLinks": 0,
        "isHeadlineBlock": false,
        "showLead": false,
        "mediaCss": ""
    },
    "brand": null,
    "caixaConteudo": null,
    "dataActualizacao": null,
    "autores": [],
    "dataSheet": null,
    "mapUrl": null,
    "tags": [
        {
            "id": 81,
            "nome": "Clima",
            "slug": "clima",
            "tagEn": null,
            "isPrincipal": false,
            "isVisible": true,
            "urlRoute": "/tclima",
            "isPrincipalParaArtigo": false,
            "isTimeLine": false,
            "forcaConteudoAberto": false,
            "follow_type": null,
            "descricao": null,
            "imagem": null,
            "html": null,
            "isForForuns": false,
            "isUsedInForuns": false
        },
        {
            "id": 207,
            "nome": "Nig\u00e9ria",
            "slug": "nigeria",
            "tagEn": null,
            "isPrincipal": false,
            "isVisible": true,
            "urlRoute": "/tnigeria",
            "isPrincipalParaArtigo": false,
            "isTimeLine": false,
            "forcaConteudoAberto": false,
            "follow_type": null,
            "descricao": null,
            "imagem": null,
            "html": null,
            "isForForuns": false,
            "isUsedInForuns": false
        },
        {
            "id": 862,
            "nome": "Mundo",
            "slug": "mundo",
            "tagEn": null,
            "isPrincipal": true,
            "isVisible": true,
            "urlRoute": "/tmundo",
            "isPrincipalParaArtigo": false,
            "isTimeLine": false,
            "forcaConteudoAberto": false,
            "follow_type": null,
            "descricao": null,
            "imagem": null,
            "html": null,
            "isForForuns": false,
            "isUsedInForuns": false
        }
    ],
    "imagens": [],
    "criticas": [],
    "videos": [],
    "fotogalerias": [],
    "ficheiros": [],
    "links": [],
    "infografias": [],
    "elementos": [],
    "fichaTecnica": [],
    "audios": [],
    "charCount": 0,
    "iconography": "",
    "isSponsorContent": false,
    "isClubeP": false,
    "isItemOpinion": false,
    "isInlineMedia": false,
    "hasManualSubtitle": true,
    "isMultipleRubric": false,
    "socialUmage": null,
    "socialTitle": "Nig\u00e9ria. Lagos vive no p\u00e2nico mas sem confrontos",
    "isLongForm": false,
    "isClosed": false,
    "isExclusive": false,
    "satelliteName": "",
    "userLibraryStatus": null,
    "maxParagraph": -1,
    "isHeadline": false,
    "wordCount": 85,
    "extra4": null,
    "partners": null,
    "props": null,
    "name": "0061970.json",
    "dct": "2002-02-05T13:21:00",
    "text": "Os rumores de combates no bairro de Agege percorreram durante toda a manh\u00e3 a cidade mas, segundo a AFP, n\u00e3o puderam ser confirmados.\n\"N\u00e3o h\u00e1 nenhum confronto hoje em Lagos\", disse Mike Okiro, chefe da pol\u00edcia.\n\"Os rumores correm em v\u00e1rios bairros, como em Agege, Ajegunle, Obalende, criando p\u00e2nico. Mas n\u00e3o h\u00e1 nada. A situa\u00e7\u00e3o est\u00e1 calma, mais calma do que nunca\", confirmou Okiro.\nDesde s\u00e1bado passado que entre as etnias Yorouba e Hausa se t\u00eam verificado confrontos, espalhando o p\u00e2nico por v\u00e1rias zonas habitadas.",
    "language": "portuguese"
}