{
    "id": 57508,
    "titulo": "PT burlada em mais de dois milh\u00f5es de contos",
    "tituloNoticia": "PT burlada em mais de dois milh\u00f5es de contos",
    "tituloOriginal": null,
    "descricao": "",
    "textoAlternativo": null,
    "url": "/2002/01/07/sociedade/noticia/pt-burlada-em-mais-de-dois-milhoes-de-contos-57508",
    "multimediaPrincipal": "https://imagens.publico.pt/imagens.aspx/39357?tp=UH&db=IMAGENS&type=JPG",
    "multimediaPrincipalLegenda": "",
    "hasLive": false,
    "pontuacao": null,
    "numeroComentarios": 0,
    "lead": "A Portugal Telecom (PT) acumulou at\u00e9 Maio de 2001 cerca de dois milh\u00f5es de contos de preju\u00edzos em consequ\u00eancia, na maior parte das vezes, de burlas praticadas por empresas de audiotexto. Depois dessa data, e apesar de algumas altera\u00e7\u00f5es na legisla\u00e7\u00e3o, as burlas continuam a suceder-se, sendo agora os clientes os principais lesados. S\u00f3 na \u00e1rea de Lisboa, os montantes em causa j\u00e1 ultrapassam os 50 mil contos.",
    "shortUrl": "/n57508",
    "titulo_Mobile": null,
    "subtitulo": "Chamadas de valor acrescentado",
    "rubricTag": null,
    "rubrica": "Chamadas de valor acrescentado",
    "rubricUrl": null,
    "tipo": "NOTICIA",
    "emActualizacao": false,
    "fechaComentarios": false,
    "emDirecto": false,
    "facebook": 0,
    "twitter": 0,
    "google": 0,
    "fonteMultimediaPrincipal": "IMAGENS",
    "palavraChave": null,
    "itemId": "NOTICIA_57508",
    "tokenTipo": null,
    "numPartilhas": 0,
    "numComentarios": 0,
    "html": null,
    "tipoLayout": "MULTIMEDIA_NORMAL",
    "caixaId": null,
    "isOpinion": false,
    "fullUrl": "/2002/01/07/sociedade/noticia/pt-burlada-em-mais-de-dois-milhoes-de-contos-57508",
    "prioridade": 3,
    "isPreview": false,
    "escondeImagem": false,
    "aoMinuto": false,
    "isFeature": false,
    "slug": "pt-burlada-em-mais-de-dois-milhoes-de-contos-57508",
    "cleanTitle": "PT burlada em mais de dois milh\u00f5es de contos",
    "isHtml": false,
    "shareUrl": "https://www.publico.pt/2002/01/07/sociedade/noticia/pt-burlada-em-mais-de-dois-milhoes-de-contos-57508",
    "newsUrls": [],
    "isImagePortait": false,
    "cardInfo": {
        "css": [
            "card--f",
            "tone--news"
        ],
        "showMedia": false,
        "maxLinks": 0,
        "isHeadlineBlock": false,
        "showLead": false,
        "mediaCss": ""
    },
    "brand": null,
    "caixaConteudo": null,
    "dataActualizacao": null,
    "autores": [],
    "dataSheet": null,
    "mapUrl": null,
    "tags": [
        {
            "id": 523,
            "nome": "Portugal Telecom",
            "slug": "portugal-telecom",
            "tagEn": null,
            "isPrincipal": false,
            "isVisible": true,
            "urlRoute": "/tportugal-telecom",
            "isPrincipalParaArtigo": false,
            "isTimeLine": false,
            "forcaConteudoAberto": false,
            "follow_type": null,
            "descricao": null,
            "imagem": null,
            "html": null,
            "isForForuns": false,
            "isUsedInForuns": false
        },
        {
            "id": 644,
            "nome": "Lisboa",
            "slug": "lisboa",
            "tagEn": null,
            "isPrincipal": false,
            "isVisible": true,
            "urlRoute": "/tlisboa",
            "isPrincipalParaArtigo": false,
            "isTimeLine": false,
            "forcaConteudoAberto": false,
            "follow_type": null,
            "descricao": null,
            "imagem": null,
            "html": null,
            "isForForuns": false,
            "isUsedInForuns": false
        },
        {
            "id": 871,
            "nome": "Sociedade",
            "slug": "sociedade",
            "tagEn": null,
            "isPrincipal": true,
            "isVisible": true,
            "urlRoute": "/tsociedade",
            "isPrincipalParaArtigo": false,
            "isTimeLine": false,
            "forcaConteudoAberto": false,
            "follow_type": null,
            "descricao": null,
            "imagem": null,
            "html": null,
            "isForForuns": false,
            "isUsedInForuns": false
        },
        {
            "id": 905,
            "nome": "Empresas",
            "slug": "empresas",
            "tagEn": null,
            "isPrincipal": false,
            "isVisible": true,
            "urlRoute": "/tempresas",
            "isPrincipalParaArtigo": false,
            "isTimeLine": false,
            "forcaConteudoAberto": false,
            "follow_type": null,
            "descricao": null,
            "imagem": null,
            "html": null,
            "isForForuns": false,
            "isUsedInForuns": false
        }
    ],
    "imagens": [
        {
            "w": null,
            "h": null,
            "largura": null,
            "altura": null,
            "nome": "39357_telefone.jpg",
            "legenda": "",
            "autor": "P\u00daBLICO",
            "tipo": "JPG",
            "url": "https://imagens.publico.pt/imagens.aspx/39357?tp=UH&db=IMAGENS&type=JPG",
            "is_vertical": false,
            "tags": null,
            "translations": null
        }
    ],
    "criticas": [],
    "videos": [],
    "fotogalerias": [],
    "ficheiros": [],
    "links": [],
    "infografias": [],
    "elementos": [],
    "fichaTecnica": [],
    "audios": [],
    "charCount": 0,
    "iconography": "",
    "isSponsorContent": false,
    "isClubeP": false,
    "isItemOpinion": false,
    "isInlineMedia": false,
    "hasManualSubtitle": true,
    "isMultipleRubric": false,
    "socialUmage": null,
    "socialTitle": "Chamadas de valor acrescentado. PT burlada em mais de dois milh\u00f5es de contos",
    "isLongForm": false,
    "isClosed": false,
    "isExclusive": false,
    "satelliteName": "",
    "userLibraryStatus": null,
    "maxParagraph": -1,
    "isHeadline": false,
    "wordCount": 816,
    "extra4": null,
    "partners": null,
    "props": null,
    "name": "0057508.json",
    "dct": "2002-01-07T06:42:00",
    "text": "Na Directoria de Lisboa da Pol\u00edcia Judici\u00e1ria (PJ) est\u00e3o, actualmente, em investiga\u00e7\u00e3o dez processos que t\u00eam como arguidos respons\u00e1veis e trabalhadores de empresas de audiotexto. Ao todo h\u00e1 112 pessoas indiciadas pelos delitos (sobrefactura\u00e7\u00e3o relativa a chamadas de valor acrescentado). Os ofendidos conhecidos s\u00e3o j\u00e1 261. Segundo o coordenador da PJ respons\u00e1vel pela sec\u00e7\u00e3o onde correm as aludidas investiga\u00e7\u00f5es, Pedro Fel\u00edcio, a regi\u00e3o de Lisboa \u00e9 a mais fustigada por este tipo de delito, uma vez que \u00e9 ali que est\u00e3o sediadas cerca de 80 por cento das empresas nacionais de audiotexto. As burlas, conforme salientou, abrangem, contudo, gente de todo o pa\u00eds. \"\u00c9, sem d\u00favida, um tipo de crime que continua em expans\u00e3o, bastando para isso ver o n\u00famero de arguidos - dos 112 existentes na zona de ac\u00e7\u00e3o da PJ de Lisboa, 26 s\u00e3o gerentes de empresas de audiotexto, enquanto os restantes 86 s\u00e3o operadores telef\u00f3nicos -, o valor j\u00e1 apurado das burlas e, a este, somar ainda montantes ainda n\u00e3o totalmente apurados, relativos a mais 64 ofendidos\", disse ao P\u00daBLICO Pedro Fel\u00edcio. Segundo o mesmo respons\u00e1vel da Judici\u00e1ria, s\u00e3o seis os \"modus operandi\" j\u00e1 identificados para a pr\u00e1tica destas burlas. Um dos m\u00e9todos mais em voga consiste em contactar um particular que esteja a usufruir do servi\u00e7o solicitando-lhe a ced\u00eancia de diversos dados particulares. \u00c0 primeira chamada telef\u00f3nica sucede-se, normalmente, uma segunda, onde novos elementos pessoais s\u00e3o pedidos. Depois, \u00e9 pedido ao cliente que prima uma determinada tecla no seu telefone. A partir desse momento, e sabendo-se que muitas empresas de audiotexto j\u00e1 possuem equipamento que lhe permite efectuar o reencaminhamento das chamadas, o cliente passa a ser taxado com uma s\u00e9rie de factura\u00e7\u00e3o que n\u00e3o \u00e9 sua. Mais simples \u00e9 o m\u00e9todo em que os operadores ligam para os clientes e, mentindo-lhes, acabam por lhes pedir para ligarem para um outro n\u00famero, garantindo que o mesmo n\u00e3o \u00e9 de valor acrescentado, podendo assim vir a ganhar determinados pr\u00e9mios. Existe ainda o m\u00e9todo em que os clientes, induzidos por an\u00fancios de jornais, ligam para n\u00fameros que supostamente n\u00e3o s\u00e3o de valor acrescentado, procurando as mais diversas informa\u00e7\u00f5es, desde quest\u00f5es de sa\u00fade a ofertas de trabalho. Estas chamadas, em lugar de serem taxadas pela tarifa normal, acabam por ser pagas como se tivessem a usufruir de um servi\u00e7o substancialmente mais elevado. Por vezes, explicou ainda Pedro Fel\u00edcio, os operadores contactam os clientes pedindo-lhes para acederem a determinados n\u00fameros e garantindo-lhes que apenas os cinco primeiros minutos de conversa\u00e7\u00e3o s\u00e3o pagos \u00e0 tarifa normal, sendo todos os restantes \u00e0 borla. \u00c9 mais um embuste, na maior parte das vezes pago \u00e0 factura\u00e7\u00e3o das chamadas de valor acrescentado. Outra das burlas consiste na disponibiliza\u00e7\u00e3o de servi\u00e7os que, efectivamente, n\u00e3o existem, como sejam as informa\u00e7\u00f5es relativas a \"casting\", medicina, psicologia, etc. Os clientes marcam determinados n\u00fameros e acabam por receber \"consultas, conselhos e sugest\u00f5es\" de pessoal \"qualificado\" que n\u00e3o s\u00e3o mais do que os operadores das empresas de audiotexto. Por fim, igualmente em grande expans\u00e3o, est\u00e3o as burlas com recurso \u00e1 via inform\u00e1tica. Aparelhagens sofisticadas, geralmente importadas, fazem o reencaminhamento das chamadas, resultando tal facto no pagamento de elevadas quantias por servi\u00e7os que de valor muito inferior. \nA Pol\u00edcia Judici\u00e1ria tem vindo a deparar-se com grandes dificuldades na recolha de provas que possam incriminar as empresas que praticam as burlas. De acordo com Pedro Fel\u00edcio, caso existisse uma fiscaliza\u00e7\u00e3o mais apertada sobre esta actividade, os delitos e consequentes prejuizos seriam bem menores. \"Estamos a falar de empresas que aparecem e desaparecem em poucos dias, sem uma localiza\u00e7\u00e3o fixa\", acrescentou Pedro Fel\u00edcio. Segundo este respons\u00e1vel da Judici\u00e1ria a maior parte destas empresas, geradoras de lucros inclacul\u00e1veis - que lhes permitem dotar-se de equipamento altamente sofisticados e, portanto, aumantar a capacidade de praticar as burlas - nem sequer possuem registos contabil\u00edsticos. Muitas vezes as \u00fanicas pistas dos investigadores para tentarem chegar aos infractores s\u00e3o as que, eventualmente, s\u00e3o fornecidas pelos pr\u00f3prios operadores das empresas de audiotexto. \"Mas tamb\u00e9m nesse aspecto tudo \u00e9 muito dif\u00edcil. Os operadores s\u00e3o de dif\u00edcil localizal\u00e7\u00e3o, at\u00e9 porque quando falam com os clientes nunca d\u00e3o a identifica\u00e7\u00e3o correcta. Utilizam alcunhas, 'nomes de guerra'. Al\u00e9m disso n\u00e3o permanecem muito tempo na mesma empresa, antes saltitando de uma para outra. Recebem a recibos verdes e, muitas vezes, est\u00e3o ligados \u00e0 prostitui\u00e7\u00e3o. S\u00e3o pessoas experientes na forma como cometem os crimes\", adiantou o coordenador da PJ. Refira-se por fim, quais as penaliza\u00e7\u00f5es que a lei prev\u00ea para este tipo de crime. Assim, se o montante da burla for at\u00e9 800 contos, os infractores podem ser punidos com uma pena at\u00e9 tr\u00eas anos de pris\u00e3o (o que desde logo exclui a pris\u00e3o preventiva). Se o montante da burla se cifrar entre os 800 e os 3200 contos, ent\u00e3o a pena de pris\u00e3o pode ir at\u00e9 aos cinco anos. Todos os crimes cujo valor ultrapasse os 3200 contos s\u00e3o pass\u00edveis de puni\u00e7\u00e3o at\u00e9 oito anos de cadeia.",
    "language": "portuguese"
}